{
    "@schema": "https://raw.githubusercontent.com/slicer/slicer/master/Modules/Loadable/Markups/Resources/Schema/markups-schema-v1.0.3.json#",
    "markups": [
        {
            "type": "Curve",
            "coordinateSystem": "LPS",
            "coordinateUnits": "mm",
            "locked": false,
            "fixedNumberOfControlPoints": false,
            "labelFormat": "%N-%d",
            "lastUsedControlPointNumber": 4,
            "controlPoints": [
                {
                    "id": "1",
                    "label": "Network curve_1 (4)-1",
                    "description": "",
                    "associatedNodeID": "",
                    "position": [5.59222412109375, -172.787109375, 150.67010498046875],
                    "orientation": [-1.0, -0.0, -0.0, -0.0, -1.0, -0.0, 0.0, 0.0, 1.0],
                    "selected": true,
                    "locked": false,
                    "visibility": false,
                    "positionStatus": "defined"
                },
                {
                    "id": "2",
                    "label": "Network curve_1 (4)-2",
                    "description": "",
                    "associatedNodeID": "",
                    "position": [3.4428796768188477, -163.49462890625, 170.8470916748047],
                    "orientation": [-1.0, -0.0, -0.0, -0.0, -1.0, -0.0, 0.0, 0.0, 1.0],
                    "selected": true,
                    "locked": false,
                    "visibility": false,
                    "positionStatus": "defined"
                },
                {
                    "id": "3",
                    "label": "Network curve_1 (4)-3",
                    "description": "",
                    "associatedNodeID": "",
                    "position": [-0.11823663860559464, -163.88491821289063, 174.17111206054688],
                    "orientation": [-1.0, -0.0, -0.0, -0.0, -1.0, -0.0, 0.0, 0.0, 1.0],
                    "selected": true,
                    "locked": false,
                    "visibility": false,
                    "positionStatus": "defined"
                },
                {
                    "id": "4",
                    "label": "Network curve_1 (4)-4",
                    "description": "",
                    "associatedNodeID": "",
                    "position": [-1.1570875644683838, -165.047607421875, 178.2406463623047],
                    "orientation": [-1.0, -0.0, -0.0, -0.0, -1.0, -0.0, 0.0, 0.0, 1.0],
                    "selected": true,
                    "locked": false,
                    "visibility": false,
                    "positionStatus": "defined"
                }
            ],
            "measurements": [
                {
                    "name": "length",
                    "enabled": false,
                    "units": "mm",
                    "printFormat": "%-#4.4g%s"
                },
                {
                    "name": "curvature mean",
                    "enabled": false,
                    "printFormat": "%5.3f %s"
                },
                {
                    "name": "curvature max",
                    "enabled": false,
                    "printFormat": "%5.3f %s"
                },
                {
                    "name": "torsion mean",
                    "enabled": false,
                    "printFormat": "%5.3f %s"
                },
                {
                    "name": "torsion max",
                    "enabled": false,
                    "printFormat": "%5.3f %s"
                },
                {
                    "name": "Radius",
                    "enabled": true,
                    "units": "mm",
                    "controlPointValues": [
                        3.397232761834039,
                        3.397232761834039,
                        1.9370304647883727,
                        1.9370304647883727
                    ]
                }
            ],
            "display": {
                "visibility": true,
                "opacity": 1.0,
                "color": [0.4, 1.0, 1.0],
                "selectedColor": [0.7411764705882353, 0.596078431372549, 0.3058823529411765],
                "activeColor": [0.4, 1.0, 0.0],
                "propertiesLabelVisibility": true,
                "pointLabelsVisibility": false,
                "textScale": 3.0,
                "glyphType": "Sphere3D",
                "glyphScale": 3.0,
                "glyphSize": 5.0,
                "useGlyphScale": true,
                "sliceProjection": false,
                "sliceProjectionUseFiducialColor": true,
                "sliceProjectionOutlinedBehindSlicePlane": false,
                "sliceProjectionColor": [1.0, 1.0, 1.0],
                "sliceProjectionOpacity": 0.6,
                "lineThickness": 0.2,
                "lineColorFadingStart": 1.0,
                "lineColorFadingEnd": 10.0,
                "lineColorFadingSaturation": 1.0,
                "lineColorFadingHueOffset": 0.0,
                "handlesInteractive": false,
                "translationHandleVisibility": true,
                "rotationHandleVisibility": true,
                "scaleHandleVisibility": true,
                "interactionHandleScale": 3.0,
                "snapMode": "toVisibleSurface"
            }
        }
    ]
}